synchronized背后的monitor锁
---

### 获取和释放monitor锁的时机

用synchronized关键字修饰代码块或者修饰一个方法,这部分被保护的代码,在同一时刻最多只有一个线程可以运行,而synchronized背后正是利用monitor锁实现的.每个Java对象都可以用作一个实现同步的锁,这个锁也被称为内置锁或monitor锁,获得monitor锁的唯一途径是进入由这个锁保护的同步代码块或同步方法.线程在进入被synchronized保护的代码块之前,会自动获取锁,并且无论是正常退出还是抛出异常退出,在退出的时候都会自动释放锁. (有点像try..finally..)

### 同步代码块

下面是同步代码块的例子:

```java
public class SynTest {
    public void method() {
        synchronized(this){
            System.out.println("lagou");
        }
    }
}
```
然后用javap -verbose 看一下字节码,关键信息如下:

```
public void method();
    descriptor: ()V
    flags: ACC_PUBLIC
    Code:
      stack=2, locals=3, args_size=1
         0: aload_0
         1: dup
         2: astore_1
         3: monitorenter
         4: getstatic     #2                  // Field java/lang/System.out:Ljava/io/PrintStream;
         7: ldc           #3                  // String lagou
         9: invokevirtual #4                  // Method java/io/PrintStream.println:(Ljava/lang/String;)V
        12: aload_1
        13: monitorexit
        14: goto          22
        17: astore_2
        18: aload_1
        19: monitorexit
        20: aload_2
        21: athrow
        22: return
```

从上面可以看出synchronized代码块实际上是多了monitorenter和monitorexit指令.并且只有1个monitorenter却有2个monitorexit.有2个monitorexit的原因: JVM要保证每个monitorenter必须有对应的monitorexit,monitorenter指令被插入到同步代码块的开始位置,而monitorexit需要插入到方法正常结束处和异常处两个地方,这样可以保证抛异常的地方也能释放锁.

每个对象维护着一个记录着被锁次数的计数器,未被锁定的对象的该计数器为0.

**monitorenter**

执行monitorenter的线程尝试获得monitor的所有权,会发生3种情况:

- 如果该monitor的计数为0,则线程获得该monitor并将其计数设置为1.然后该线程就是这个monitor的所有者.
- 如果线程已经拥有了这个monitor,则它将重新进入,并且累加计数
- 如果其他线程已经拥有了这个monitor,那这个线程就会被阻塞.直到这个monitor的计数变成0,代表这个monitor已经被释放了,于是当前这个线程就会再次尝试获取这个monitor

**monitorexit**

monitorexit的作用是将monitor的计数器减1,直到减为0为止.代表这个monitor被释放了,已经没有任何线程拥有它了,代表着解锁.所以,其他正在等待这个monitor的线程,此时便可以再次尝试获取这个monitor的所有权.

### 同步方法

对于同步方法,javap -verbose之后,可以看到,synchronized方法和普通方法大部分是一样的,不同的是,这个方法多了一个`ACC_SYNCHRONIZED`的flag修饰符.

当某个线程要访问某个方法的时候,会首先检查方法是否有`ACC_SYNCHRONIZED`标志,如果有则需要先获得monitor锁,然后才能开始执行方法,方法执行之后再释放monitor锁.